installit/__init__.py
installit/installit.py
InstallIt-1.5.0.dist-info/LICENSE
InstallIt-1.5.0.dist-info/METADATA
InstallIt-1.5.0.dist-info/WHEEL
InstallIt-1.5.0.dist-info/top_level.txt
InstallIt-1.5.0.dist-info/RECORD
